sidd/About.py
sidd/Experiences.py
sidd/Projects.py
sidd/Resume.py
sidd/__init__.py
sidd/home.py
sidd/main.py
SiddP6-0.5.0.dist-info/LICENSE
SiddP6-0.5.0.dist-info/METADATA
SiddP6-0.5.0.dist-info/WHEEL
SiddP6-0.5.0.dist-info/top_level.txt
SiddP6-0.5.0.dist-info/RECORD
