Metadata-Version: 2.1
Name: SiddP6
Version: 0.5.0
Summary: Siddhartha Purwar portfolio pip package
Home-page: UNKNOWN
Author: Siddhartha Purwar
License: UNKNOWN
Platform: UNKNOWN
Classifier: Programming Language :: Python :: 3
Classifier: License :: OSI Approved :: MIT License
Classifier: Operating System :: OS Independent
Requires-Python: >=3.6
License-File: LICENSE
Requires-Dist: streamlit==1.40.0
